{
  "name": "Noir Corne",
  "rarity": 1,
  "profession": "Defender",
  "potential": [
    {
      "description": "DP Cost -1",
      "cost": -1.0
    },
    {
      "description": "Max HP +45",
      "maxHp": 45.0
    },
    {
      "description": "Redeployment Time -5 sec",
      "respawn": -5.0
    },
    {
      "description": "Max HP +45",
      "maxHp": 45.0
    },
    {
      "description": "DP Cost -1",
      "cost": -1.0
    }
  ],
  "stats": {
    "level": 30,
    "maxHp": 1670,
    "atk": 240,
    "def": 315,
    "res": 0.0,
    "cost": 14,
    "block": 3,
    "atkSpd": 100.0,
    "atkTime": 1.2,
    "hpRec": 0.0,
    "spRecoveryPerSec": 1.0,
    "respawn": 70
  },
  "talents": [
    {
      "name": "Improved Armor",
      "description": "Max HP and DEF +12%",
      "blackboard": {
        "max_hp": 0.12,
        "def": 0.12
      }
    }
  ],
  "trust": {
    "def": 40
  }
}