{
  "name": "Vigna",
  "rarity": 3,
  "profession": "Vanguard",
  "potential": [
    {
      "description": "DP Cost -1",
      "cost": -1.0
    },
    {
      "description": "Redeployment Time -4 sec",
      "respawn": -4.0
    },
    {
      "description": "ATK +24",
      "atk": 24.0
    },
    {
      "description": "Improves Talent"
    },
    {
      "description": "DP Cost -1",
      "cost": -1.0
    }
  ],
  "skills": [
    "skchr_vigna_2",
    {
      "skillId": "skchr_vigna_1",
      "iconId": "skcom_atk_up[2]",
      "hidden": false,
      "levels": {
        "name": "ATK Up \u03b2",
        "rangeId": null,
        "description": "ATK +80%",
        "skillType": 1,
        "spData": {
          "spType": 1,
          "levelUpCost": null,
          "maxChargeTime": 1,
          "spCost": 35,
          "initSp": 10,
          "increment": 1.0
        },
        "prefabId": "skchr_vigna_1",
        "duration": 25.0,
        "blackboard": {
          "atk": 0.8
        }
      }
    }
  ],
  "stats": {
    "level": 70,
    "maxHp": 1845,
    "atk": 558,
    "def": 351,
    "res": 0.0,
    "cost": 11,
    "block": 1,
    "atkSpd": 100.0,
    "atkTime": 1.0,
    "hpRec": 0.0,
    "spRecoveryPerSec": 1.0,
    "respawn": 70
  },
  "talents": [
    {
      "name": "Fierce Stabbing",
      "description": "When attacking, has a 10% chance to increase the current damage of that attack by 110% <@ba.talpu>(+10%). The chance increases to 30% when Vigna\u2019s skill is active.",
      "blackboard": {
        "atk": 1.1,
        "prob1": 0.1,
        "prob2": 0.3
      }
    }
  ],
  "trait": [
    {
      "cost": 1.0
    }
  ],
  "trust": {
    "atk": 60
  }
}